vibrato-0.2.0.dist-info/METADATA
vibrato-0.2.0.dist-info/WHEEL
vibrato-0.2.0.dist-info/license_files/LICENSE-APACHE
vibrato-0.2.0.dist-info/license_files/LICENSE-MIT
vibrato/__init__.py
vibrato/__init__.pyi
vibrato/py.typed
vibrato/vibrato.cp310-win32.pyd
vibrato-0.2.0.dist-info/RECORD
