Metadata-Version: 2.1
Name: vibrato
Version: 0.2.0
License-File: LICENSE-APACHE
License-File: LICENSE-MIT
